README.md
setup.py
pico_rbgkeypad.egg-info/PKG-INFO
pico_rbgkeypad.egg-info/SOURCES.txt
pico_rbgkeypad.egg-info/dependency_links.txt
pico_rbgkeypad.egg-info/top_level.txt
rgbkeypad/__init__.py
rgbkeypad/rgbkeypad.py