Metadata-Version: 2.1
Name: pico-rbgkeypad
Version: 0.2.0
Summary: 0.2.0
Home-page: https://github.com/martinohanlon/pico-rbgkeypad
Author: Martin O'Hanlon
Author-email: martin@ohanlonweb.com
License: MIT
Keywords: raspberry,pi,pico,rgb,keypad,pimoroni
Platform: UNKNOWN
Classifier: Development Status :: 4 - Beta
Classifier: Intended Audience :: Developers
Classifier: Programming Language :: Python :: Implementation :: MicroPython
